odoo/addons/account_invoice_facturx/README.rst
odoo/addons/account_invoice_facturx/__init__.py
odoo/addons/account_invoice_facturx/__manifest__.py
odoo/addons/account_invoice_facturx/hooks.py
odoo/addons/account_invoice_facturx/i18n/account_invoice_factur-x.pot
odoo/addons/account_invoice_facturx/i18n/account_invoice_facturx.pot
odoo/addons/account_invoice_facturx/i18n/de.po
odoo/addons/account_invoice_facturx/i18n/es.po
odoo/addons/account_invoice_facturx/i18n/fr.po
odoo/addons/account_invoice_facturx/models/__init__.py
odoo/addons/account_invoice_facturx/models/account_move.py
odoo/addons/account_invoice_facturx/models/company.py
odoo/addons/account_invoice_facturx/models/ir_actions_report.py
odoo/addons/account_invoice_facturx/readme/CONFIGURE.rst
odoo/addons/account_invoice_facturx/readme/CONTRIBUTORS.rst
odoo/addons/account_invoice_facturx/readme/DESCRIPTION.rst
odoo/addons/account_invoice_facturx/readme/INSTALL.rst
odoo/addons/account_invoice_facturx/static/description/icon.png
odoo/addons/account_invoice_facturx/static/description/index.html
odoo/addons/account_invoice_facturx/static/logos/factur-x-basic.png
odoo/addons/account_invoice_facturx/static/logos/factur-x-basicwl.png
odoo/addons/account_invoice_facturx/static/logos/factur-x-en16931.png
odoo/addons/account_invoice_facturx/static/logos/factur-x-extended.png
odoo/addons/account_invoice_facturx/static/logos/factur-x-minimum.png
odoo/addons/account_invoice_facturx/tests/__init__.py
odoo/addons/account_invoice_facturx/tests/test_facturx_invoice.py
odoo/addons/account_invoice_facturx/views/report_invoice.xml
odoo/addons/account_invoice_facturx/views/res_config_settings.xml
odoo/addons/account_invoice_facturx/views/res_partner.xml
odoo/addons/account_invoice_facturx/wizards/__init__.py
odoo/addons/account_invoice_facturx/wizards/res_config_settings.py
odoo14_addon_account_invoice_facturx-14.0.1.1.3.dist-info/METADATA
odoo14_addon_account_invoice_facturx-14.0.1.1.3.dist-info/WHEEL
odoo14_addon_account_invoice_facturx-14.0.1.1.3.dist-info/top_level.txt
odoo14_addon_account_invoice_facturx-14.0.1.1.3.dist-info/RECORD
