Metadata-Version: 2.1
Name: odoo14-addon-account_invoice_facturx
Version: 14.0.1.1.3
Summary: Generate Factur-X/ZUGFeRD customer invoices
Home-page: https://github.com/OCA/edi
Author: Akretion,Odoo Community Association (OCA)
Author-email: support@odoo-community.org
License: AGPL-3
Classifier: Programming Language :: Python
Classifier: Framework :: Odoo
Classifier: Framework :: Odoo :: 14.0
Classifier: License :: OSI Approved :: GNU Affero General Public License v3
Requires-Python: >=3.6
Requires-Dist: factur-x<=3.1
Requires-Dist: odoo14-addon-account-einvoice-generate
Requires-Dist: odoo14-addon-account-payment-partner
Requires-Dist: odoo14-addon-base-facturx
Requires-Dist: odoo<14.1dev,>=14.0a
